directmessages/__init__.py
directmessages/admin.py
directmessages/apps.py
directmessages/models.py
directmessages/services.py
directmessages/signals.py
directmessages/tests.py
directmessages/migrations/0001_initial.py
directmessages/migrations/0002_auto_20160721_1822.py
directmessages/migrations/__init__.py
django_directmessages-0.9.1.dist-info/DESCRIPTION.rst
django_directmessages-0.9.1.dist-info/METADATA
django_directmessages-0.9.1.dist-info/RECORD
django_directmessages-0.9.1.dist-info/WHEEL
django_directmessages-0.9.1.dist-info/metadata.json
django_directmessages-0.9.1.dist-info/top_level.txt
